README.md
setup.cfg
setup.py
liveness.egg-info/PKG-INFO
liveness.egg-info/SOURCES.txt
liveness.egg-info/dependency_links.txt
liveness.egg-info/requires.txt
liveness.egg-info/top_level.txt
src/liveness/__init__.py
src/liveness/__main__.py
src/liveness/timestamp.py