Metadata-Version: 2.1
Name: liveness
Version: 1.1.2
Summary: Library for simplifying liveness checks for python based infrastructure
Home-page: https://github.com/Cray-HPE/k8s-liveness
Author: Hewlett Packard Enterprise Development LP
Author-email: cray-oss@hpe.com
License: UNKNOWN
Download-URL: https://github.com/Cray-HPE/k8s-liveness/archive/liveness-1.1.2.tar.gz
Keywords: Cray/HPE Kubernetes Liveness Helm
Platform: UNKNOWN
Classifier: Development Status :: 5 - Production/Stable
Classifier: Intended Audience :: Developers
Classifier: Topic :: Software Development :: Build Tools
Classifier: License :: OSI Approved :: MIT License
Classifier: Programming Language :: Python :: 3.6
